{
  "type": "FeatureCollection",
  "features": [
    {
      "type": "Feature",
      "properties": {
        "Feature": "PHTR",
        "Method": "GAM",
        "Data_Length": 21,
        "SiteName": "Taoyuan",
        "Date": "2023-06-09",
        "Valid_MAE": 3.112,
        "Version": "2023-06-09 00:01:39",
        "Model": "<a href=\"https://github.com/IISNRL/DCF-PM2.5/blob/master/2023/20230609/20230609-PMS5003-taoyuan.joblib\" target=\"_blank\" title=\"20230609-PMS5003-taoyuan.joblib\">Link to File</a>",
        "Config": "<a href=\"https://github.com/IISNRL/DCF-PM2.5/blob/master/2023/20230609/20230609-PMS5003-taoyuan.json\" target=\"_blank\" title=\"20230609-PMS5003-taoyuan.json\">Link to File</a>"
      },
      "geometry": {
        "type": "Point",
        "coordinates": [
          121.304,
          24.995
        ]
      }
    },
    {
      "type": "Feature",
      "properties": {
        "Feature": "PHTR",
        "Method": "GAM",
        "Data_Length": 7,
        "SiteName": "Zhongming",
        "Date": "2023-06-09",
        "Valid_MAE": 2.878,
        "Version": "2023-06-09 00:01:55",
        "Model": "<a href=\"https://github.com/IISNRL/DCF-PM2.5/blob/master/2023/20230609/20230609-PMS5003-zhongming.joblib\" target=\"_blank\" title=\"20230609-PMS5003-zhongming.joblib\">Link to File</a>",
        "Config": "<a href=\"https://github.com/IISNRL/DCF-PM2.5/blob/master/2023/20230609/20230609-PMS5003-zhongming.json\" target=\"_blank\" title=\"20230609-PMS5003-zhongming.json\">Link to File</a>"
      },
      "geometry": {
        "type": "Point",
        "coordinates": [
          120.641,
          24.152
        ]
      }
    },
    {
      "type": "Feature",
      "properties": {
        "Feature": "PHT",
        "Method": "GAM",
        "Data_Length": 14,
        "SiteName": "Wanhua",
        "Date": "2023-06-09",
        "Valid_MAE": 5.236,
        "Version": "2023-06-09 00:02:22",
        "Model": "<a href=\"https://github.com/IISNRL/DCF-PM2.5/blob/master/2023/20230609/20230609-PMS5003-wanhua.joblib\" target=\"_blank\" title=\"20230609-PMS5003-wanhua.joblib\">Link to File</a>",
        "Config": "<a href=\"https://github.com/IISNRL/DCF-PM2.5/blob/master/2023/20230609/20230609-PMS5003-wanhua.json\" target=\"_blank\" title=\"20230609-PMS5003-wanhua.json\">Link to File</a>"
      },
      "geometry": {
        "type": "Point",
        "coordinates": [
          121.508,
          25.047
        ]
      }
    }
  ]
}