{
  "type": "FeatureCollection",
  "features": [
    {
      "type": "Feature",
      "properties": {
        "Feature": "P",
        "Method": "SVR",
        "Data_Length": 7,
        "SiteName": "Taoyuan",
        "Date": "2023-06-02",
        "Valid_MAE": 4.073,
        "Version": "2023-06-02 00:01:48",
        "Model": "<a href=\"https://github.com/IISNRL/DCF-PM2.5/blob/master/2023/20230602/20230602-PMS5003-taoyuan.joblib\" target=\"_blank\" title=\"20230602-PMS5003-taoyuan.joblib\">Link to File</a>",
        "Config": "<a href=\"https://github.com/IISNRL/DCF-PM2.5/blob/master/2023/20230602/20230602-PMS5003-taoyuan.json\" target=\"_blank\" title=\"20230602-PMS5003-taoyuan.json\">Link to File</a>"
      },
      "geometry": {
        "type": "Point",
        "coordinates": [
          121.304,
          24.995
        ]
      }
    },
    {
      "type": "Feature",
      "properties": {
        "Feature": "PH",
        "Method": "SVR",
        "Data_Length": 14,
        "SiteName": "Zhongming",
        "Date": "2023-06-02",
        "Valid_MAE": 2.921,
        "Version": "2023-06-02 00:01:49",
        "Model": "<a href=\"https://github.com/IISNRL/DCF-PM2.5/blob/master/2023/20230602/20230602-PMS5003-zhongming.joblib\" target=\"_blank\" title=\"20230602-PMS5003-zhongming.joblib\">Link to File</a>",
        "Config": "<a href=\"https://github.com/IISNRL/DCF-PM2.5/blob/master/2023/20230602/20230602-PMS5003-zhongming.json\" target=\"_blank\" title=\"20230602-PMS5003-zhongming.json\">Link to File</a>"
      },
      "geometry": {
        "type": "Point",
        "coordinates": [
          120.641,
          24.152
        ]
      }
    },
    {
      "type": "Feature",
      "properties": {
        "Feature": "PHR",
        "Method": "GAM",
        "Data_Length": 14,
        "SiteName": "Wanhua",
        "Date": "2023-06-02",
        "Valid_MAE": 2.816,
        "Version": "2023-06-02 00:01:51",
        "Model": "<a href=\"https://github.com/IISNRL/DCF-PM2.5/blob/master/2023/20230602/20230602-PMS5003-wanhua.joblib\" target=\"_blank\" title=\"20230602-PMS5003-wanhua.joblib\">Link to File</a>",
        "Config": "<a href=\"https://github.com/IISNRL/DCF-PM2.5/blob/master/2023/20230602/20230602-PMS5003-wanhua.json\" target=\"_blank\" title=\"20230602-PMS5003-wanhua.json\">Link to File</a>"
      },
      "geometry": {
        "type": "Point",
        "coordinates": [
          121.508,
          25.047
        ]
      }
    }
  ]
}