{
  "type": "FeatureCollection",
  "features": [
    {
      "type": "Feature",
      "properties": {
        "Feature": "PHTR",
        "Method": "LinearRegression",
        "Data_Length": 14,
        "SiteName": "Taoyuan",
        "Date": "2023-03-14",
        "Valid_MAE": 3.39,
        "Version": "2023-03-14 00:03:02",
        "Model": "<a href=\"https://github.com/IISNRL/DCF-PM2.5/blob/master/2023/20230314/20230314-PMS5003-taoyuan.joblib\" target=\"_blank\" title=\"20230314-PMS5003-taoyuan.joblib\">Link to File</a>",
        "Config": "<a href=\"https://github.com/IISNRL/DCF-PM2.5/blob/master/2023/20230314/20230314-PMS5003-taoyuan.json\" target=\"_blank\" title=\"20230314-PMS5003-taoyuan.json\">Link to File</a>"
      },
      "geometry": {
        "type": "Point",
        "coordinates": [
          121.304,
          24.995
        ]
      }
    },
    {
      "type": "Feature",
      "properties": {
        "Feature": "PHTR",
        "Method": "LinearRegression",
        "Data_Length": 7,
        "SiteName": "Zhongming",
        "Date": "2023-03-14",
        "Valid_MAE": 3.557,
        "Version": "2023-03-14 00:03:08",
        "Model": "<a href=\"https://github.com/IISNRL/DCF-PM2.5/blob/master/2023/20230314/20230314-PMS5003-zhongming.joblib\" target=\"_blank\" title=\"20230314-PMS5003-zhongming.joblib\">Link to File</a>",
        "Config": "<a href=\"https://github.com/IISNRL/DCF-PM2.5/blob/master/2023/20230314/20230314-PMS5003-zhongming.json\" target=\"_blank\" title=\"20230314-PMS5003-zhongming.json\">Link to File</a>"
      },
      "geometry": {
        "type": "Point",
        "coordinates": [
          120.641,
          24.152
        ]
      }
    },
    {
      "type": "Feature",
      "properties": {
        "Feature": "PHR",
        "Method": "SVR",
        "Data_Length": 14,
        "SiteName": "Wanhua",
        "Date": "2023-03-14",
        "Valid_MAE": 2.217,
        "Version": "2023-03-14 00:03:14",
        "Model": "<a href=\"https://github.com/IISNRL/DCF-PM2.5/blob/master/2023/20230314/20230314-PMS5003-wanhua.joblib\" target=\"_blank\" title=\"20230314-PMS5003-wanhua.joblib\">Link to File</a>",
        "Config": "<a href=\"https://github.com/IISNRL/DCF-PM2.5/blob/master/2023/20230314/20230314-PMS5003-wanhua.json\" target=\"_blank\" title=\"20230314-PMS5003-wanhua.json\">Link to File</a>"
      },
      "geometry": {
        "type": "Point",
        "coordinates": [
          121.508,
          25.047
        ]
      }
    }
  ]
}