{
  "type": "FeatureCollection",
  "features": [
    {
      "type": "Feature",
      "properties": {
        "Feature": "PTR",
        "Method": "RandomForestRegressor",
        "Data_Length": 21,
        "SiteName": "Taoyuan",
        "Date": "2023-11-13",
        "Valid_MAE": 4.498,
        "Version": "2023-11-13 00:02:28",
        "Model": "<a href=\"https://github.com/IISNRL/DCF-PM2.5/blob/master/2023/20231113/20231113-PMS5003-taoyuan.joblib\" target=\"_blank\" title=\"20231113-PMS5003-taoyuan.joblib\">Link to File</a>",
        "Config": "<a href=\"https://github.com/IISNRL/DCF-PM2.5/blob/master/2023/20231113/20231113-PMS5003-taoyuan.json\" target=\"_blank\" title=\"20231113-PMS5003-taoyuan.json\">Link to File</a>"
      },
      "geometry": {
        "type": "Point",
        "coordinates": [
          121.304,
          24.995
        ]
      }
    },
    {
      "type": "Feature",
      "properties": {
        "Feature": "PT",
        "Method": "SVR",
        "Data_Length": 14,
        "SiteName": "Zhongming",
        "Date": "2023-11-13",
        "Valid_MAE": 2.696,
        "Version": "2023-11-13 00:03:05",
        "Model": "<a href=\"https://github.com/IISNRL/DCF-PM2.5/blob/master/2023/20231113/20231113-PMS5003-zhongming.joblib\" target=\"_blank\" title=\"20231113-PMS5003-zhongming.joblib\">Link to File</a>",
        "Config": "<a href=\"https://github.com/IISNRL/DCF-PM2.5/blob/master/2023/20231113/20231113-PMS5003-zhongming.json\" target=\"_blank\" title=\"20231113-PMS5003-zhongming.json\">Link to File</a>"
      },
      "geometry": {
        "type": "Point",
        "coordinates": [
          120.641,
          24.152
        ]
      }
    }
  ]
}