{
  "type": "FeatureCollection",
  "features": [
    {
      "type": "Feature",
      "properties": {
        "Feature": "P",
        "Method": "SVR",
        "Data_Length": 7,
        "SiteName": "Taoyuan",
        "Date": "2023-08-10",
        "Valid_MAE": 3.375,
        "Version": "2023-08-10 00:01:50",
        "Model": "<a href=\"https://github.com/IISNRL/DCF-PM2.5/blob/master/2023/20230810/20230810-PMS5003-taoyuan.joblib\" target=\"_blank\" title=\"20230810-PMS5003-taoyuan.joblib\">Link to File</a>",
        "Config": "<a href=\"https://github.com/IISNRL/DCF-PM2.5/blob/master/2023/20230810/20230810-PMS5003-taoyuan.json\" target=\"_blank\" title=\"20230810-PMS5003-taoyuan.json\">Link to File</a>"
      },
      "geometry": {
        "type": "Point",
        "coordinates": [
          121.304,
          24.995
        ]
      }
    },
    {
      "type": "Feature",
      "properties": {
        "Feature": "P",
        "Method": "SVR",
        "Data_Length": 7,
        "SiteName": "Zhongming",
        "Date": "2023-08-10",
        "Valid_MAE": 2.563,
        "Version": "2023-08-10 00:01:55",
        "Model": "<a href=\"https://github.com/IISNRL/DCF-PM2.5/blob/master/2023/20230810/20230810-PMS5003-zhongming.joblib\" target=\"_blank\" title=\"20230810-PMS5003-zhongming.joblib\">Link to File</a>",
        "Config": "<a href=\"https://github.com/IISNRL/DCF-PM2.5/blob/master/2023/20230810/20230810-PMS5003-zhongming.json\" target=\"_blank\" title=\"20230810-PMS5003-zhongming.json\">Link to File</a>"
      },
      "geometry": {
        "type": "Point",
        "coordinates": [
          120.641,
          24.152
        ]
      }
    }
  ]
}