{
  "type": "FeatureCollection",
  "features": [
    {
      "type": "Feature",
      "properties": {
        "Feature": "PH",
        "Method": "SVR",
        "Data_Length": 7,
        "SiteName": "Banqiao",
        "Date": "2023-01-13",
        "Valid_MAE": 3.208,
        "Version": "2023-01-13 00:03:58",
        "Model": "<a href=\"https://github.com/IISNRL/DCF-PM2.5/blob/master/2023/20230113/20230113-PMS5003-banqiao.joblib\" target=\"_blank\" title=\"20230113-PMS5003-banqiao.joblib\">Link to File</a>",
        "Config": "<a href=\"https://github.com/IISNRL/DCF-PM2.5/blob/master/2023/20230113/20230113-PMS5003-banqiao.json\" target=\"_blank\" title=\"20230113-PMS5003-banqiao.json\">Link to File</a>"
      },
      "geometry": {
        "type": "Point",
        "coordinates": [
          121.459,
          25.013
        ]
      }
    },
    {
      "type": "Feature",
      "properties": {
        "Feature": "PHT",
        "Method": "BayesianRidge",
        "Data_Length": 7,
        "SiteName": "Taoyuan",
        "Date": "2023-01-13",
        "Valid_MAE": 3.487,
        "Version": "2023-01-13 00:04:06",
        "Model": "<a href=\"https://github.com/IISNRL/DCF-PM2.5/blob/master/2023/20230113/20230113-PMS5003-taoyuan.joblib\" target=\"_blank\" title=\"20230113-PMS5003-taoyuan.joblib\">Link to File</a>",
        "Config": "<a href=\"https://github.com/IISNRL/DCF-PM2.5/blob/master/2023/20230113/20230113-PMS5003-taoyuan.json\" target=\"_blank\" title=\"20230113-PMS5003-taoyuan.json\">Link to File</a>"
      },
      "geometry": {
        "type": "Point",
        "coordinates": [
          121.304,
          24.995
        ]
      }
    },
    {
      "type": "Feature",
      "properties": {
        "Feature": "PTR",
        "Method": "RidgeRegression",
        "Data_Length": 7,
        "SiteName": "Zhongming",
        "Date": "2023-01-13",
        "Valid_MAE": 3.582,
        "Version": "2023-01-13 00:04:13",
        "Model": "<a href=\"https://github.com/IISNRL/DCF-PM2.5/blob/master/2023/20230113/20230113-PMS5003-zhongming.joblib\" target=\"_blank\" title=\"20230113-PMS5003-zhongming.joblib\">Link to File</a>",
        "Config": "<a href=\"https://github.com/IISNRL/DCF-PM2.5/blob/master/2023/20230113/20230113-PMS5003-zhongming.json\" target=\"_blank\" title=\"20230113-PMS5003-zhongming.json\">Link to File</a>"
      },
      "geometry": {
        "type": "Point",
        "coordinates": [
          120.641,
          24.152
        ]
      }
    },
    {
      "type": "Feature",
      "properties": {
        "Feature": "PTR",
        "Method": "GAM",
        "Data_Length": 30,
        "SiteName": "Wanhua",
        "Date": "2023-01-13",
        "Valid_MAE": 2.518,
        "Version": "2023-01-13 00:04:21",
        "Model": "<a href=\"https://github.com/IISNRL/DCF-PM2.5/blob/master/2023/20230113/20230113-PMS5003-wanhua.joblib\" target=\"_blank\" title=\"20230113-PMS5003-wanhua.joblib\">Link to File</a>",
        "Config": "<a href=\"https://github.com/IISNRL/DCF-PM2.5/blob/master/2023/20230113/20230113-PMS5003-wanhua.json\" target=\"_blank\" title=\"20230113-PMS5003-wanhua.json\">Link to File</a>"
      },
      "geometry": {
        "type": "Point",
        "coordinates": [
          121.508,
          25.047
        ]
      }
    }
  ]
}