{
  "type": "FeatureCollection",
  "features": [
    {
      "type": "Feature",
      "properties": {
        "Feature": "PHT",
        "Method": "RandomForestRegressor",
        "Data_Length": 7,
        "SiteName": "Taoyuan",
        "Date": "2023-09-13",
        "Valid_MAE": 2.311,
        "Version": "2023-09-13 00:01:34",
        "Model": "<a href=\"https://github.com/IISNRL/DCF-PM2.5/blob/master/2023/20230913/20230913-PMS5003-taoyuan.joblib\" target=\"_blank\" title=\"20230913-PMS5003-taoyuan.joblib\">Link to File</a>",
        "Config": "<a href=\"https://github.com/IISNRL/DCF-PM2.5/blob/master/2023/20230913/20230913-PMS5003-taoyuan.json\" target=\"_blank\" title=\"20230913-PMS5003-taoyuan.json\">Link to File</a>"
      },
      "geometry": {
        "type": "Point",
        "coordinates": [
          121.304,
          24.995
        ]
      }
    },
    {
      "type": "Feature",
      "properties": {
        "Feature": "PHR",
        "Method": "SVR",
        "Data_Length": 30,
        "SiteName": "Zhongming",
        "Date": "2023-09-13",
        "Valid_MAE": 1.859,
        "Version": "2023-09-13 00:01:43",
        "Model": "<a href=\"https://github.com/IISNRL/DCF-PM2.5/blob/master/2023/20230913/20230913-PMS5003-zhongming.joblib\" target=\"_blank\" title=\"20230913-PMS5003-zhongming.joblib\">Link to File</a>",
        "Config": "<a href=\"https://github.com/IISNRL/DCF-PM2.5/blob/master/2023/20230913/20230913-PMS5003-zhongming.json\" target=\"_blank\" title=\"20230913-PMS5003-zhongming.json\">Link to File</a>"
      },
      "geometry": {
        "type": "Point",
        "coordinates": [
          120.641,
          24.152
        ]
      }
    }
  ]
}