{
  "type": "FeatureCollection",
  "features": [
    {
      "type": "Feature",
      "properties": {
        "Feature": "P",
        "Method": "GAM",
        "Data_Length": 14,
        "SiteName": "Taoyuan",
        "Date": "2023-02-20",
        "Valid_MAE": 4.59,
        "Version": "2023-02-20 00:03:47",
        "Model": "<a href=\"https://github.com/IISNRL/DCF-PM2.5/blob/master/2023/20230220/20230220-PMS5003-taoyuan.joblib\" target=\"_blank\" title=\"20230220-PMS5003-taoyuan.joblib\">Link to File</a>",
        "Config": "<a href=\"https://github.com/IISNRL/DCF-PM2.5/blob/master/2023/20230220/20230220-PMS5003-taoyuan.json\" target=\"_blank\" title=\"20230220-PMS5003-taoyuan.json\">Link to File</a>"
      },
      "geometry": {
        "type": "Point",
        "coordinates": [
          121.304,
          24.995
        ]
      }
    },
    {
      "type": "Feature",
      "properties": {
        "Feature": "PHT",
        "Method": "SVR",
        "Data_Length": 21,
        "SiteName": "Zhongming",
        "Date": "2023-02-20",
        "Valid_MAE": 3.605,
        "Version": "2023-02-20 00:03:53",
        "Model": "<a href=\"https://github.com/IISNRL/DCF-PM2.5/blob/master/2023/20230220/20230220-PMS5003-zhongming.joblib\" target=\"_blank\" title=\"20230220-PMS5003-zhongming.joblib\">Link to File</a>",
        "Config": "<a href=\"https://github.com/IISNRL/DCF-PM2.5/blob/master/2023/20230220/20230220-PMS5003-zhongming.json\" target=\"_blank\" title=\"20230220-PMS5003-zhongming.json\">Link to File</a>"
      },
      "geometry": {
        "type": "Point",
        "coordinates": [
          120.641,
          24.152
        ]
      }
    },
    {
      "type": "Feature",
      "properties": {
        "Feature": "PHT",
        "Method": "GAM",
        "Data_Length": 30,
        "SiteName": "Wanhua",
        "Date": "2023-02-20",
        "Valid_MAE": 3.316,
        "Version": "2023-02-20 00:04:01",
        "Model": "<a href=\"https://github.com/IISNRL/DCF-PM2.5/blob/master/2023/20230220/20230220-PMS5003-wanhua.joblib\" target=\"_blank\" title=\"20230220-PMS5003-wanhua.joblib\">Link to File</a>",
        "Config": "<a href=\"https://github.com/IISNRL/DCF-PM2.5/blob/master/2023/20230220/20230220-PMS5003-wanhua.json\" target=\"_blank\" title=\"20230220-PMS5003-wanhua.json\">Link to File</a>"
      },
      "geometry": {
        "type": "Point",
        "coordinates": [
          121.508,
          25.047
        ]
      }
    }
  ]
}