{
  "type": "FeatureCollection",
  "features": [
    {
      "type": "Feature",
      "properties": {
        "Feature": "PT",
        "Method": "SVR",
        "Data_Length": 21,
        "SiteName": "Taoyuan",
        "Date": "2023-07-06",
        "Valid_MAE": 2.549,
        "Version": "2023-07-06 00:02:24",
        "Model": "<a href=\"https://github.com/IISNRL/DCF-PM2.5/blob/master/2023/20230706/20230706-PMS5003-taoyuan.joblib\" target=\"_blank\" title=\"20230706-PMS5003-taoyuan.joblib\">Link to File</a>",
        "Config": "<a href=\"https://github.com/IISNRL/DCF-PM2.5/blob/master/2023/20230706/20230706-PMS5003-taoyuan.json\" target=\"_blank\" title=\"20230706-PMS5003-taoyuan.json\">Link to File</a>"
      },
      "geometry": {
        "type": "Point",
        "coordinates": [
          121.304,
          24.995
        ]
      }
    },
    {
      "type": "Feature",
      "properties": {
        "Feature": "P",
        "Method": "SVR",
        "Data_Length": 7,
        "SiteName": "Zhongming",
        "Date": "2023-07-06",
        "Valid_MAE": 2.115,
        "Version": "2023-07-06 00:02:35",
        "Model": "<a href=\"https://github.com/IISNRL/DCF-PM2.5/blob/master/2023/20230706/20230706-PMS5003-zhongming.joblib\" target=\"_blank\" title=\"20230706-PMS5003-zhongming.joblib\">Link to File</a>",
        "Config": "<a href=\"https://github.com/IISNRL/DCF-PM2.5/blob/master/2023/20230706/20230706-PMS5003-zhongming.json\" target=\"_blank\" title=\"20230706-PMS5003-zhongming.json\">Link to File</a>"
      },
      "geometry": {
        "type": "Point",
        "coordinates": [
          120.641,
          24.152
        ]
      }
    },
    {
      "type": "Feature",
      "properties": {
        "Feature": "PHR",
        "Method": "GAM",
        "Data_Length": 30,
        "SiteName": "Wanhua",
        "Date": "2023-07-06",
        "Valid_MAE": 5.179,
        "Version": "2023-07-06 00:02:36",
        "Model": "<a href=\"https://github.com/IISNRL/DCF-PM2.5/blob/master/2023/20230706/20230706-PMS5003-wanhua.joblib\" target=\"_blank\" title=\"20230706-PMS5003-wanhua.joblib\">Link to File</a>",
        "Config": "<a href=\"https://github.com/IISNRL/DCF-PM2.5/blob/master/2023/20230706/20230706-PMS5003-wanhua.json\" target=\"_blank\" title=\"20230706-PMS5003-wanhua.json\">Link to File</a>"
      },
      "geometry": {
        "type": "Point",
        "coordinates": [
          121.508,
          25.047
        ]
      }
    }
  ]
}