{
  "type": "FeatureCollection",
  "features": [
    {
      "type": "Feature",
      "properties": {
        "Feature": "PHR",
        "Method": "RandomForestRegressor",
        "Data_Length": 21,
        "SiteName": "Taoyuan",
        "Date": "2023-11-12",
        "Valid_MAE": 4.155,
        "Version": "2023-11-12 00:02:24",
        "Model": "<a href=\"https://github.com/IISNRL/DCF-PM2.5/blob/master/2023/20231112/20231112-PMS5003-taoyuan.joblib\" target=\"_blank\" title=\"20231112-PMS5003-taoyuan.joblib\">Link to File</a>",
        "Config": "<a href=\"https://github.com/IISNRL/DCF-PM2.5/blob/master/2023/20231112/20231112-PMS5003-taoyuan.json\" target=\"_blank\" title=\"20231112-PMS5003-taoyuan.json\">Link to File</a>"
      },
      "geometry": {
        "type": "Point",
        "coordinates": [
          121.304,
          24.995
        ]
      }
    },
    {
      "type": "Feature",
      "properties": {
        "Feature": "PHT",
        "Method": "SVR",
        "Data_Length": 30,
        "SiteName": "Zhongming",
        "Date": "2023-11-12",
        "Valid_MAE": 2.287,
        "Version": "2023-11-12 00:02:50",
        "Model": "<a href=\"https://github.com/IISNRL/DCF-PM2.5/blob/master/2023/20231112/20231112-PMS5003-zhongming.joblib\" target=\"_blank\" title=\"20231112-PMS5003-zhongming.joblib\">Link to File</a>",
        "Config": "<a href=\"https://github.com/IISNRL/DCF-PM2.5/blob/master/2023/20231112/20231112-PMS5003-zhongming.json\" target=\"_blank\" title=\"20231112-PMS5003-zhongming.json\">Link to File</a>"
      },
      "geometry": {
        "type": "Point",
        "coordinates": [
          120.641,
          24.152
        ]
      }
    }
  ]
}