{
  "type": "FeatureCollection",
  "features": [
    {
      "type": "Feature",
      "properties": {
        "Feature": "PR",
        "Method": "GAM",
        "Data_Length": 14,
        "SiteName": "Taoyuan",
        "Date": "2023-09-27",
        "Valid_MAE": 5.83,
        "Version": "2023-09-27 00:01:48",
        "Model": "<a href=\"https://github.com/IISNRL/DCF-PM2.5/blob/master/2023/20230927/20230927-PMS5003-taoyuan.joblib\" target=\"_blank\" title=\"20230927-PMS5003-taoyuan.joblib\">Link to File</a>",
        "Config": "<a href=\"https://github.com/IISNRL/DCF-PM2.5/blob/master/2023/20230927/20230927-PMS5003-taoyuan.json\" target=\"_blank\" title=\"20230927-PMS5003-taoyuan.json\">Link to File</a>"
      },
      "geometry": {
        "type": "Point",
        "coordinates": [
          121.304,
          24.995
        ]
      }
    },
    {
      "type": "Feature",
      "properties": {
        "Feature": "PTR",
        "Method": "LinearRegression",
        "Data_Length": 14,
        "SiteName": "Zhongming",
        "Date": "2023-09-27",
        "Valid_MAE": 2.274,
        "Version": "2023-09-27 00:02:05",
        "Model": "<a href=\"https://github.com/IISNRL/DCF-PM2.5/blob/master/2023/20230927/20230927-PMS5003-zhongming.joblib\" target=\"_blank\" title=\"20230927-PMS5003-zhongming.joblib\">Link to File</a>",
        "Config": "<a href=\"https://github.com/IISNRL/DCF-PM2.5/blob/master/2023/20230927/20230927-PMS5003-zhongming.json\" target=\"_blank\" title=\"20230927-PMS5003-zhongming.json\">Link to File</a>"
      },
      "geometry": {
        "type": "Point",
        "coordinates": [
          120.641,
          24.152
        ]
      }
    }
  ]
}