{
  "type": "FeatureCollection",
  "features": [
    {
      "type": "Feature",
      "properties": {
        "Feature": "PT",
        "Method": "GAM",
        "Data_Length": 21,
        "SiteName": "Taoyuan",
        "Date": "2023-02-25",
        "Valid_MAE": 3.59,
        "Version": "2023-02-25 00:03:21",
        "Model": "<a href=\"https://github.com/IISNRL/DCF-PM2.5/blob/master/2023/20230225/20230225-PMS5003-taoyuan.joblib\" target=\"_blank\" title=\"20230225-PMS5003-taoyuan.joblib\">Link to File</a>",
        "Config": "<a href=\"https://github.com/IISNRL/DCF-PM2.5/blob/master/2023/20230225/20230225-PMS5003-taoyuan.json\" target=\"_blank\" title=\"20230225-PMS5003-taoyuan.json\">Link to File</a>"
      },
      "geometry": {
        "type": "Point",
        "coordinates": [
          121.304,
          24.995
        ]
      }
    },
    {
      "type": "Feature",
      "properties": {
        "Feature": "PTR",
        "Method": "SVR",
        "Data_Length": 21,
        "SiteName": "Zhongming",
        "Date": "2023-02-25",
        "Valid_MAE": 3.767,
        "Version": "2023-02-25 00:03:42",
        "Model": "<a href=\"https://github.com/IISNRL/DCF-PM2.5/blob/master/2023/20230225/20230225-PMS5003-zhongming.joblib\" target=\"_blank\" title=\"20230225-PMS5003-zhongming.joblib\">Link to File</a>",
        "Config": "<a href=\"https://github.com/IISNRL/DCF-PM2.5/blob/master/2023/20230225/20230225-PMS5003-zhongming.json\" target=\"_blank\" title=\"20230225-PMS5003-zhongming.json\">Link to File</a>"
      },
      "geometry": {
        "type": "Point",
        "coordinates": [
          120.641,
          24.152
        ]
      }
    },
    {
      "type": "Feature",
      "properties": {
        "Feature": "PH",
        "Method": "GAM",
        "Data_Length": 21,
        "SiteName": "Wanhua",
        "Date": "2023-02-25",
        "Valid_MAE": 3.01,
        "Version": "2023-02-25 00:03:52",
        "Model": "<a href=\"https://github.com/IISNRL/DCF-PM2.5/blob/master/2023/20230225/20230225-PMS5003-wanhua.joblib\" target=\"_blank\" title=\"20230225-PMS5003-wanhua.joblib\">Link to File</a>",
        "Config": "<a href=\"https://github.com/IISNRL/DCF-PM2.5/blob/master/2023/20230225/20230225-PMS5003-wanhua.json\" target=\"_blank\" title=\"20230225-PMS5003-wanhua.json\">Link to File</a>"
      },
      "geometry": {
        "type": "Point",
        "coordinates": [
          121.508,
          25.047
        ]
      }
    }
  ]
}