{
  "type": "FeatureCollection",
  "features": [
    {
      "type": "Feature",
      "properties": {
        "Feature": "PT",
        "Method": "GAM",
        "Data_Length": 21,
        "SiteName": "Taoyuan",
        "Date": "2023-05-27",
        "Valid_MAE": 3.824,
        "Version": "2023-05-27 00:02:17",
        "Model": "<a href=\"https://github.com/IISNRL/DCF-PM2.5/blob/master/2023/20230527/20230527-PMS5003-taoyuan.joblib\" target=\"_blank\" title=\"20230527-PMS5003-taoyuan.joblib\">Link to File</a>",
        "Config": "<a href=\"https://github.com/IISNRL/DCF-PM2.5/blob/master/2023/20230527/20230527-PMS5003-taoyuan.json\" target=\"_blank\" title=\"20230527-PMS5003-taoyuan.json\">Link to File</a>"
      },
      "geometry": {
        "type": "Point",
        "coordinates": [
          121.304,
          24.995
        ]
      }
    },
    {
      "type": "Feature",
      "properties": {
        "Feature": "PTR",
        "Method": "RidgeRegression",
        "Data_Length": 30,
        "SiteName": "Zhongming",
        "Date": "2023-05-27",
        "Valid_MAE": 2.8,
        "Version": "2023-05-27 00:02:31",
        "Model": "<a href=\"https://github.com/IISNRL/DCF-PM2.5/blob/master/2023/20230527/20230527-PMS5003-zhongming.joblib\" target=\"_blank\" title=\"20230527-PMS5003-zhongming.joblib\">Link to File</a>",
        "Config": "<a href=\"https://github.com/IISNRL/DCF-PM2.5/blob/master/2023/20230527/20230527-PMS5003-zhongming.json\" target=\"_blank\" title=\"20230527-PMS5003-zhongming.json\">Link to File</a>"
      },
      "geometry": {
        "type": "Point",
        "coordinates": [
          120.641,
          24.152
        ]
      }
    },
    {
      "type": "Feature",
      "properties": {
        "Feature": "PTR",
        "Method": "SVR",
        "Data_Length": 30,
        "SiteName": "Wanhua",
        "Date": "2023-05-27",
        "Valid_MAE": 2.898,
        "Version": "2023-05-27 00:02:43",
        "Model": "<a href=\"https://github.com/IISNRL/DCF-PM2.5/blob/master/2023/20230527/20230527-PMS5003-wanhua.joblib\" target=\"_blank\" title=\"20230527-PMS5003-wanhua.joblib\">Link to File</a>",
        "Config": "<a href=\"https://github.com/IISNRL/DCF-PM2.5/blob/master/2023/20230527/20230527-PMS5003-wanhua.json\" target=\"_blank\" title=\"20230527-PMS5003-wanhua.json\">Link to File</a>"
      },
      "geometry": {
        "type": "Point",
        "coordinates": [
          121.508,
          25.047
        ]
      }
    }
  ]
}