{
  "type": "FeatureCollection",
  "features": [
    {
      "type": "Feature",
      "properties": {
        "Feature": "PHT",
        "Method": "SVR",
        "Data_Length": 14,
        "SiteName": "Taoyuan",
        "Date": "2023-11-26",
        "Valid_MAE": 5.226,
        "Version": "2023-11-26 00:01:18",
        "Model": "<a href=\"https://github.com/IISNRL/DCF-PM2.5/blob/master/2023/20231126/20231126-PMS5003-taoyuan.joblib\" target=\"_blank\" title=\"20231126-PMS5003-taoyuan.joblib\">Link to File</a>",
        "Config": "<a href=\"https://github.com/IISNRL/DCF-PM2.5/blob/master/2023/20231126/20231126-PMS5003-taoyuan.json\" target=\"_blank\" title=\"20231126-PMS5003-taoyuan.json\">Link to File</a>"
      },
      "geometry": {
        "type": "Point",
        "coordinates": [
          121.304,
          24.995
        ]
      }
    },
    {
      "type": "Feature",
      "properties": {
        "Feature": "PH",
        "Method": "BayesianRidge",
        "Data_Length": 21,
        "SiteName": "Zhongming",
        "Date": "2023-11-26",
        "Valid_MAE": 3.133,
        "Version": "2023-11-26 00:01:20",
        "Model": "<a href=\"https://github.com/IISNRL/DCF-PM2.5/blob/master/2023/20231126/20231126-PMS5003-zhongming.joblib\" target=\"_blank\" title=\"20231126-PMS5003-zhongming.joblib\">Link to File</a>",
        "Config": "<a href=\"https://github.com/IISNRL/DCF-PM2.5/blob/master/2023/20231126/20231126-PMS5003-zhongming.json\" target=\"_blank\" title=\"20231126-PMS5003-zhongming.json\">Link to File</a>"
      },
      "geometry": {
        "type": "Point",
        "coordinates": [
          120.641,
          24.152
        ]
      }
    }
  ]
}