{
  "type": "FeatureCollection",
  "features": [
    {
      "type": "Feature",
      "properties": {
        "Feature": "PH",
        "Method": "GAM",
        "Data_Length": 30,
        "SiteName": "Taoyuan",
        "Date": "2023-04-05",
        "Valid_MAE": 4.616,
        "Version": "2023-04-05 00:02:29",
        "Model": "<a href=\"https://github.com/IISNRL/DCF-PM2.5/blob/master/2023/20230405/20230405-PMS5003-taoyuan.joblib\" target=\"_blank\" title=\"20230405-PMS5003-taoyuan.joblib\">Link to File</a>",
        "Config": "<a href=\"https://github.com/IISNRL/DCF-PM2.5/blob/master/2023/20230405/20230405-PMS5003-taoyuan.json\" target=\"_blank\" title=\"20230405-PMS5003-taoyuan.json\">Link to File</a>"
      },
      "geometry": {
        "type": "Point",
        "coordinates": [
          121.304,
          24.995
        ]
      }
    },
    {
      "type": "Feature",
      "properties": {
        "Feature": "P",
        "Method": "SVR",
        "Data_Length": 30,
        "SiteName": "Zhongming",
        "Date": "2023-04-05",
        "Valid_MAE": 4.521,
        "Version": "2023-04-05 00:02:46",
        "Model": "<a href=\"https://github.com/IISNRL/DCF-PM2.5/blob/master/2023/20230405/20230405-PMS5003-zhongming.joblib\" target=\"_blank\" title=\"20230405-PMS5003-zhongming.joblib\">Link to File</a>",
        "Config": "<a href=\"https://github.com/IISNRL/DCF-PM2.5/blob/master/2023/20230405/20230405-PMS5003-zhongming.json\" target=\"_blank\" title=\"20230405-PMS5003-zhongming.json\">Link to File</a>"
      },
      "geometry": {
        "type": "Point",
        "coordinates": [
          120.641,
          24.152
        ]
      }
    },
    {
      "type": "Feature",
      "properties": {
        "Feature": "PTR",
        "Method": "LassoRegression",
        "Data_Length": 30,
        "SiteName": "Wanhua",
        "Date": "2023-04-05",
        "Valid_MAE": 3.104,
        "Version": "2023-04-05 00:02:53",
        "Model": "<a href=\"https://github.com/IISNRL/DCF-PM2.5/blob/master/2023/20230405/20230405-PMS5003-wanhua.joblib\" target=\"_blank\" title=\"20230405-PMS5003-wanhua.joblib\">Link to File</a>",
        "Config": "<a href=\"https://github.com/IISNRL/DCF-PM2.5/blob/master/2023/20230405/20230405-PMS5003-wanhua.json\" target=\"_blank\" title=\"20230405-PMS5003-wanhua.json\">Link to File</a>"
      },
      "geometry": {
        "type": "Point",
        "coordinates": [
          121.508,
          25.047
        ]
      }
    }
  ]
}