{
  "type": "FeatureCollection",
  "features": [
    {
      "type": "Feature",
      "properties": {
        "Feature": "PR",
        "Method": "BayesianRidge",
        "Data_Length": 30,
        "SiteName": "Taoyuan",
        "Date": "2023-09-05",
        "Valid_MAE": 2.989,
        "Version": "2023-09-05 00:00:38",
        "Model": "<a href=\"https://github.com/IISNRL/DCF-PM2.5/blob/master/2023/20230905/20230905-PMS5003-taoyuan.joblib\" target=\"_blank\" title=\"20230905-PMS5003-taoyuan.joblib\">Link to File</a>",
        "Config": "<a href=\"https://github.com/IISNRL/DCF-PM2.5/blob/master/2023/20230905/20230905-PMS5003-taoyuan.json\" target=\"_blank\" title=\"20230905-PMS5003-taoyuan.json\">Link to File</a>"
      },
      "geometry": {
        "type": "Point",
        "coordinates": [
          121.304,
          24.995
        ]
      }
    },
    {
      "type": "Feature",
      "properties": {
        "Feature": "PHR",
        "Method": "RandomForestRegressor",
        "Data_Length": 30,
        "SiteName": "Zhongming",
        "Date": "2023-09-05",
        "Valid_MAE": 2.128,
        "Version": "2023-09-05 00:00:42",
        "Model": "<a href=\"https://github.com/IISNRL/DCF-PM2.5/blob/master/2023/20230905/20230905-PMS5003-zhongming.joblib\" target=\"_blank\" title=\"20230905-PMS5003-zhongming.joblib\">Link to File</a>",
        "Config": "<a href=\"https://github.com/IISNRL/DCF-PM2.5/blob/master/2023/20230905/20230905-PMS5003-zhongming.json\" target=\"_blank\" title=\"20230905-PMS5003-zhongming.json\">Link to File</a>"
      },
      "geometry": {
        "type": "Point",
        "coordinates": [
          120.641,
          24.152
        ]
      }
    }
  ]
}