{
  "type": "FeatureCollection",
  "features": [
    {
      "type": "Feature",
      "properties": {
        "Feature": "PHT",
        "Method": "GAM",
        "Data_Length": 21,
        "SiteName": "Taoyuan",
        "Date": "2023-07-18",
        "Valid_MAE": 3.05,
        "Version": "2023-07-18 00:02:43",
        "Model": "<a href=\"https://github.com/IISNRL/DCF-PM2.5/blob/master/2023/20230718/20230718-PMS5003-taoyuan.joblib\" target=\"_blank\" title=\"20230718-PMS5003-taoyuan.joblib\">Link to File</a>",
        "Config": "<a href=\"https://github.com/IISNRL/DCF-PM2.5/blob/master/2023/20230718/20230718-PMS5003-taoyuan.json\" target=\"_blank\" title=\"20230718-PMS5003-taoyuan.json\">Link to File</a>"
      },
      "geometry": {
        "type": "Point",
        "coordinates": [
          121.304,
          24.995
        ]
      }
    },
    {
      "type": "Feature",
      "properties": {
        "Feature": "PHTR",
        "Method": "RandomForestRegressor",
        "Data_Length": 21,
        "SiteName": "Zhongming",
        "Date": "2023-07-18",
        "Valid_MAE": 1.949,
        "Version": "2023-07-18 00:03:05",
        "Model": "<a href=\"https://github.com/IISNRL/DCF-PM2.5/blob/master/2023/20230718/20230718-PMS5003-zhongming.joblib\" target=\"_blank\" title=\"20230718-PMS5003-zhongming.joblib\">Link to File</a>",
        "Config": "<a href=\"https://github.com/IISNRL/DCF-PM2.5/blob/master/2023/20230718/20230718-PMS5003-zhongming.json\" target=\"_blank\" title=\"20230718-PMS5003-zhongming.json\">Link to File</a>"
      },
      "geometry": {
        "type": "Point",
        "coordinates": [
          120.641,
          24.152
        ]
      }
    }
  ]
}