{
  "type": "FeatureCollection",
  "features": [
    {
      "type": "Feature",
      "properties": {
        "Feature": "P",
        "Method": "BayesianRidge",
        "Data_Length": 21,
        "SiteName": "Taoyuan",
        "Date": "2023-05-01",
        "Valid_MAE": 5.252,
        "Version": "2023-05-01 00:01:54",
        "Model": "<a href=\"https://github.com/IISNRL/DCF-PM2.5/blob/master/2023/20230501/20230501-PMS5003-taoyuan.joblib\" target=\"_blank\" title=\"20230501-PMS5003-taoyuan.joblib\">Link to File</a>",
        "Config": "<a href=\"https://github.com/IISNRL/DCF-PM2.5/blob/master/2023/20230501/20230501-PMS5003-taoyuan.json\" target=\"_blank\" title=\"20230501-PMS5003-taoyuan.json\">Link to File</a>"
      },
      "geometry": {
        "type": "Point",
        "coordinates": [
          121.304,
          24.995
        ]
      }
    },
    {
      "type": "Feature",
      "properties": {
        "Feature": "PH",
        "Method": "GAM",
        "Data_Length": 21,
        "SiteName": "Zhongming",
        "Date": "2023-05-01",
        "Valid_MAE": 5.16,
        "Version": "2023-05-01 00:01:58",
        "Model": "<a href=\"https://github.com/IISNRL/DCF-PM2.5/blob/master/2023/20230501/20230501-PMS5003-zhongming.joblib\" target=\"_blank\" title=\"20230501-PMS5003-zhongming.joblib\">Link to File</a>",
        "Config": "<a href=\"https://github.com/IISNRL/DCF-PM2.5/blob/master/2023/20230501/20230501-PMS5003-zhongming.json\" target=\"_blank\" title=\"20230501-PMS5003-zhongming.json\">Link to File</a>"
      },
      "geometry": {
        "type": "Point",
        "coordinates": [
          120.641,
          24.152
        ]
      }
    },
    {
      "type": "Feature",
      "properties": {
        "Feature": "PTR",
        "Method": "GAM",
        "Data_Length": 14,
        "SiteName": "Wanhua",
        "Date": "2023-05-01",
        "Valid_MAE": 5.503,
        "Version": "2023-05-01 00:02:23",
        "Model": "<a href=\"https://github.com/IISNRL/DCF-PM2.5/blob/master/2023/20230501/20230501-PMS5003-wanhua.joblib\" target=\"_blank\" title=\"20230501-PMS5003-wanhua.joblib\">Link to File</a>",
        "Config": "<a href=\"https://github.com/IISNRL/DCF-PM2.5/blob/master/2023/20230501/20230501-PMS5003-wanhua.json\" target=\"_blank\" title=\"20230501-PMS5003-wanhua.json\">Link to File</a>"
      },
      "geometry": {
        "type": "Point",
        "coordinates": [
          121.508,
          25.047
        ]
      }
    }
  ]
}