{
  "type": "FeatureCollection",
  "features": [
    {
      "type": "Feature",
      "properties": {
        "Feature": "PT",
        "Method": "RandomForestRegressor",
        "Data_Length": 30,
        "SiteName": "Taoyuan",
        "Date": "2023-04-14",
        "Valid_MAE": 4.293,
        "Version": "2023-04-14 00:02:18",
        "Model": "<a href=\"https://github.com/IISNRL/DCF-PM2.5/blob/master/2023/20230414/20230414-PMS5003-taoyuan.joblib\" target=\"_blank\" title=\"20230414-PMS5003-taoyuan.joblib\">Link to File</a>",
        "Config": "<a href=\"https://github.com/IISNRL/DCF-PM2.5/blob/master/2023/20230414/20230414-PMS5003-taoyuan.json\" target=\"_blank\" title=\"20230414-PMS5003-taoyuan.json\">Link to File</a>"
      },
      "geometry": {
        "type": "Point",
        "coordinates": [
          121.304,
          24.995
        ]
      }
    },
    {
      "type": "Feature",
      "properties": {
        "Feature": "PTR",
        "Method": "RandomForestRegressor",
        "Data_Length": 7,
        "SiteName": "Zhongming",
        "Date": "2023-04-14",
        "Valid_MAE": 7.019,
        "Version": "2023-04-14 00:02:46",
        "Model": "<a href=\"https://github.com/IISNRL/DCF-PM2.5/blob/master/2023/20230414/20230414-PMS5003-zhongming.joblib\" target=\"_blank\" title=\"20230414-PMS5003-zhongming.joblib\">Link to File</a>",
        "Config": "<a href=\"https://github.com/IISNRL/DCF-PM2.5/blob/master/2023/20230414/20230414-PMS5003-zhongming.json\" target=\"_blank\" title=\"20230414-PMS5003-zhongming.json\">Link to File</a>"
      },
      "geometry": {
        "type": "Point",
        "coordinates": [
          120.641,
          24.152
        ]
      }
    },
    {
      "type": "Feature",
      "properties": {
        "Feature": "P",
        "Method": "RandomForestRegressor",
        "Data_Length": 7,
        "SiteName": "Wanhua",
        "Date": "2023-04-14",
        "Valid_MAE": 3.744,
        "Version": "2023-04-14 00:03:09",
        "Model": "<a href=\"https://github.com/IISNRL/DCF-PM2.5/blob/master/2023/20230414/20230414-PMS5003-wanhua.joblib\" target=\"_blank\" title=\"20230414-PMS5003-wanhua.joblib\">Link to File</a>",
        "Config": "<a href=\"https://github.com/IISNRL/DCF-PM2.5/blob/master/2023/20230414/20230414-PMS5003-wanhua.json\" target=\"_blank\" title=\"20230414-PMS5003-wanhua.json\">Link to File</a>"
      },
      "geometry": {
        "type": "Point",
        "coordinates": [
          121.508,
          25.047
        ]
      }
    }
  ]
}