{
  "type": "FeatureCollection",
  "features": [
    {
      "type": "Feature",
      "properties": {
        "Feature": "PHT",
        "Method": "SVR",
        "Data_Length": 14,
        "SiteName": "Taoyuan",
        "Date": "2023-05-13",
        "Valid_MAE": 3.621,
        "Version": "2023-05-13 00:02:33",
        "Model": "<a href=\"https://github.com/IISNRL/DCF-PM2.5/blob/master/2023/20230513/20230513-PMS5003-taoyuan.joblib\" target=\"_blank\" title=\"20230513-PMS5003-taoyuan.joblib\">Link to File</a>",
        "Config": "<a href=\"https://github.com/IISNRL/DCF-PM2.5/blob/master/2023/20230513/20230513-PMS5003-taoyuan.json\" target=\"_blank\" title=\"20230513-PMS5003-taoyuan.json\">Link to File</a>"
      },
      "geometry": {
        "type": "Point",
        "coordinates": [
          121.304,
          24.995
        ]
      }
    },
    {
      "type": "Feature",
      "properties": {
        "Feature": "PHT",
        "Method": "GAM",
        "Data_Length": 14,
        "SiteName": "Zhongming",
        "Date": "2023-05-13",
        "Valid_MAE": 2.887,
        "Version": "2023-05-13 00:02:40",
        "Model": "<a href=\"https://github.com/IISNRL/DCF-PM2.5/blob/master/2023/20230513/20230513-PMS5003-zhongming.joblib\" target=\"_blank\" title=\"20230513-PMS5003-zhongming.joblib\">Link to File</a>",
        "Config": "<a href=\"https://github.com/IISNRL/DCF-PM2.5/blob/master/2023/20230513/20230513-PMS5003-zhongming.json\" target=\"_blank\" title=\"20230513-PMS5003-zhongming.json\">Link to File</a>"
      },
      "geometry": {
        "type": "Point",
        "coordinates": [
          120.641,
          24.152
        ]
      }
    },
    {
      "type": "Feature",
      "properties": {
        "Feature": "PHT",
        "Method": "SVR",
        "Data_Length": 14,
        "SiteName": "Wanhua",
        "Date": "2023-05-13",
        "Valid_MAE": 3.062,
        "Version": "2023-05-13 00:02:57",
        "Model": "<a href=\"https://github.com/IISNRL/DCF-PM2.5/blob/master/2023/20230513/20230513-PMS5003-wanhua.joblib\" target=\"_blank\" title=\"20230513-PMS5003-wanhua.joblib\">Link to File</a>",
        "Config": "<a href=\"https://github.com/IISNRL/DCF-PM2.5/blob/master/2023/20230513/20230513-PMS5003-wanhua.json\" target=\"_blank\" title=\"20230513-PMS5003-wanhua.json\">Link to File</a>"
      },
      "geometry": {
        "type": "Point",
        "coordinates": [
          121.508,
          25.047
        ]
      }
    }
  ]
}