{
  "type": "FeatureCollection",
  "features": [
    {
      "type": "Feature",
      "properties": {
        "Feature": "PTR",
        "Method": "RandomForestRegressor",
        "Data_Length": 7,
        "SiteName": "Taoyuan",
        "Date": "2023-12-01",
        "Valid_MAE": 6.215,
        "Version": "2023-12-01 00:01:27",
        "Model": "<a href=\"https://github.com/IISNRL/DCF-PM2.5/blob/master/2023/20231201/20231201-PMS5003-taoyuan.joblib\" target=\"_blank\" title=\"20231201-PMS5003-taoyuan.joblib\">Link to File</a>",
        "Config": "<a href=\"https://github.com/IISNRL/DCF-PM2.5/blob/master/2023/20231201/20231201-PMS5003-taoyuan.json\" target=\"_blank\" title=\"20231201-PMS5003-taoyuan.json\">Link to File</a>"
      },
      "geometry": {
        "type": "Point",
        "coordinates": [
          121.304,
          24.995
        ]
      }
    },
    {
      "type": "Feature",
      "properties": {
        "Feature": "PHR",
        "Method": "GAM",
        "Data_Length": 30,
        "SiteName": "Zhongming",
        "Date": "2023-12-01",
        "Valid_MAE": 2.726,
        "Version": "2023-12-01 00:01:33",
        "Model": "<a href=\"https://github.com/IISNRL/DCF-PM2.5/blob/master/2023/20231201/20231201-PMS5003-zhongming.joblib\" target=\"_blank\" title=\"20231201-PMS5003-zhongming.joblib\">Link to File</a>",
        "Config": "<a href=\"https://github.com/IISNRL/DCF-PM2.5/blob/master/2023/20231201/20231201-PMS5003-zhongming.json\" target=\"_blank\" title=\"20231201-PMS5003-zhongming.json\">Link to File</a>"
      },
      "geometry": {
        "type": "Point",
        "coordinates": [
          120.641,
          24.152
        ]
      }
    }
  ]
}