{
  "type": "FeatureCollection",
  "features": [
    {
      "type": "Feature",
      "properties": {
        "Feature": "PTR",
        "Method": "SVR",
        "Data_Length": 30,
        "SiteName": "Taoyuan",
        "Date": "2024-04-01",
        "Valid_MAE": 6.389,
        "Version": "2024-04-01 00:01:29",
        "Model": "<a href=\"https://github.com/IISNRL/DCF-PM2.5/blob/master/2024/20240401/20240401-PMS5003-taoyuan.joblib\" target=\"_blank\" title=\"20240401-PMS5003-taoyuan.joblib\">Link to File</a>",
        "Config": "<a href=\"https://github.com/IISNRL/DCF-PM2.5/blob/master/2024/20240401/20240401-PMS5003-taoyuan.json\" target=\"_blank\" title=\"20240401-PMS5003-taoyuan.json\">Link to File</a>"
      },
      "geometry": {
        "type": "Point",
        "coordinates": [
          121.304,
          24.995
        ]
      }
    },
    {
      "type": "Feature",
      "properties": {
        "Feature": "PHR",
        "Method": "SVR",
        "Data_Length": 30,
        "SiteName": "Zhongming",
        "Date": "2024-04-01",
        "Valid_MAE": 3.445,
        "Version": "2024-04-01 00:01:33",
        "Model": "<a href=\"https://github.com/IISNRL/DCF-PM2.5/blob/master/2024/20240401/20240401-PMS5003-zhongming.joblib\" target=\"_blank\" title=\"20240401-PMS5003-zhongming.joblib\">Link to File</a>",
        "Config": "<a href=\"https://github.com/IISNRL/DCF-PM2.5/blob/master/2024/20240401/20240401-PMS5003-zhongming.json\" target=\"_blank\" title=\"20240401-PMS5003-zhongming.json\">Link to File</a>"
      },
      "geometry": {
        "type": "Point",
        "coordinates": [
          120.641,
          24.152
        ]
      }
    },
    {
      "type": "Feature",
      "properties": {
        "Feature": "PHTR",
        "Method": "GAM",
        "Data_Length": 14,
        "SiteName": "Wanhua",
        "Date": "2024-04-01",
        "Valid_MAE": 3.02,
        "Version": "2024-04-01 00:01:36",
        "Model": "<a href=\"https://github.com/IISNRL/DCF-PM2.5/blob/master/2024/20240401/20240401-PMS5003-wanhua.joblib\" target=\"_blank\" title=\"20240401-PMS5003-wanhua.joblib\">Link to File</a>",
        "Config": "<a href=\"https://github.com/IISNRL/DCF-PM2.5/blob/master/2024/20240401/20240401-PMS5003-wanhua.json\" target=\"_blank\" title=\"20240401-PMS5003-wanhua.json\">Link to File</a>"
      },
      "geometry": {
        "type": "Point",
        "coordinates": [
          121.508,
          25.047
        ]
      }
    }
  ]
}