{
  "type": "FeatureCollection",
  "features": [
    {
      "type": "Feature",
      "properties": {
        "Feature": "P",
        "Method": "RandomForestRegressor",
        "Data_Length": 7,
        "SiteName": "Taoyuan",
        "Date": "2024-03-16",
        "Valid_MAE": 7.401,
        "Version": "2024-03-16 00:01:36",
        "Model": "<a href=\"https://github.com/IISNRL/DCF-PM2.5/blob/master/2024/20240316/20240316-PMS5003-taoyuan.joblib\" target=\"_blank\" title=\"20240316-PMS5003-taoyuan.joblib\">Link to File</a>",
        "Config": "<a href=\"https://github.com/IISNRL/DCF-PM2.5/blob/master/2024/20240316/20240316-PMS5003-taoyuan.json\" target=\"_blank\" title=\"20240316-PMS5003-taoyuan.json\">Link to File</a>"
      },
      "geometry": {
        "type": "Point",
        "coordinates": [
          121.304,
          24.995
        ]
      }
    },
    {
      "type": "Feature",
      "properties": {
        "Feature": "PHT",
        "Method": "GAM",
        "Data_Length": 30,
        "SiteName": "Zhongming",
        "Date": "2024-03-16",
        "Valid_MAE": 3.067,
        "Version": "2024-03-16 00:01:42",
        "Model": "<a href=\"https://github.com/IISNRL/DCF-PM2.5/blob/master/2024/20240316/20240316-PMS5003-zhongming.joblib\" target=\"_blank\" title=\"20240316-PMS5003-zhongming.joblib\">Link to File</a>",
        "Config": "<a href=\"https://github.com/IISNRL/DCF-PM2.5/blob/master/2024/20240316/20240316-PMS5003-zhongming.json\" target=\"_blank\" title=\"20240316-PMS5003-zhongming.json\">Link to File</a>"
      },
      "geometry": {
        "type": "Point",
        "coordinates": [
          120.641,
          24.152
        ]
      }
    },
    {
      "type": "Feature",
      "properties": {
        "Feature": "PHTR",
        "Method": "GAM",
        "Data_Length": 21,
        "SiteName": "Wanhua",
        "Date": "2024-03-16",
        "Valid_MAE": 3.165,
        "Version": "2024-03-16 00:01:48",
        "Model": "<a href=\"https://github.com/IISNRL/DCF-PM2.5/blob/master/2024/20240316/20240316-PMS5003-wanhua.joblib\" target=\"_blank\" title=\"20240316-PMS5003-wanhua.joblib\">Link to File</a>",
        "Config": "<a href=\"https://github.com/IISNRL/DCF-PM2.5/blob/master/2024/20240316/20240316-PMS5003-wanhua.json\" target=\"_blank\" title=\"20240316-PMS5003-wanhua.json\">Link to File</a>"
      },
      "geometry": {
        "type": "Point",
        "coordinates": [
          121.508,
          25.047
        ]
      }
    }
  ]
}