{
  "type": "FeatureCollection",
  "features": [
    {
      "type": "Feature",
      "properties": {
        "Feature": "PR",
        "Method": "RandomForestRegressor",
        "Data_Length": 7,
        "SiteName": "Taoyuan",
        "Date": "2024-05-21",
        "Valid_MAE": 3.926,
        "Version": "2024-05-21 00:01:20",
        "Model": "<a href=\"https://github.com/IISNRL/DCF-PM2.5/blob/master/2024/20240521/20240521-PMS5003-taoyuan.joblib\" target=\"_blank\" title=\"20240521-PMS5003-taoyuan.joblib\">Link to File</a>",
        "Config": "<a href=\"https://github.com/IISNRL/DCF-PM2.5/blob/master/2024/20240521/20240521-PMS5003-taoyuan.json\" target=\"_blank\" title=\"20240521-PMS5003-taoyuan.json\">Link to File</a>"
      },
      "geometry": {
        "type": "Point",
        "coordinates": [
          121.304,
          24.995
        ]
      }
    },
    {
      "type": "Feature",
      "properties": {
        "Feature": "PHTR",
        "Method": "GAM",
        "Data_Length": 14,
        "SiteName": "Zhongming",
        "Date": "2024-05-21",
        "Valid_MAE": 2.919,
        "Version": "2024-05-21 00:01:25",
        "Model": "<a href=\"https://github.com/IISNRL/DCF-PM2.5/blob/master/2024/20240521/20240521-PMS5003-zhongming.joblib\" target=\"_blank\" title=\"20240521-PMS5003-zhongming.joblib\">Link to File</a>",
        "Config": "<a href=\"https://github.com/IISNRL/DCF-PM2.5/blob/master/2024/20240521/20240521-PMS5003-zhongming.json\" target=\"_blank\" title=\"20240521-PMS5003-zhongming.json\">Link to File</a>"
      },
      "geometry": {
        "type": "Point",
        "coordinates": [
          120.641,
          24.152
        ]
      }
    },
    {
      "type": "Feature",
      "properties": {
        "Feature": "PHT",
        "Method": "RidgeRegression",
        "Data_Length": 30,
        "SiteName": "Wanhua",
        "Date": "2024-05-21",
        "Valid_MAE": 4.114,
        "Version": "2024-05-21 00:01:28",
        "Model": "<a href=\"https://github.com/IISNRL/DCF-PM2.5/blob/master/2024/20240521/20240521-PMS5003-wanhua.joblib\" target=\"_blank\" title=\"20240521-PMS5003-wanhua.joblib\">Link to File</a>",
        "Config": "<a href=\"https://github.com/IISNRL/DCF-PM2.5/blob/master/2024/20240521/20240521-PMS5003-wanhua.json\" target=\"_blank\" title=\"20240521-PMS5003-wanhua.json\">Link to File</a>"
      },
      "geometry": {
        "type": "Point",
        "coordinates": [
          121.508,
          25.047
        ]
      }
    }
  ]
}