{
  "type": "FeatureCollection",
  "features": [
    {
      "type": "Feature",
      "properties": {
        "Feature": "PTR",
        "Method": "RandomForestRegressor",
        "Data_Length": 21,
        "SiteName": "Taoyuan",
        "Date": "2024-03-12",
        "Valid_MAE": 5.431,
        "Version": "2024-03-12 00:01:25",
        "Model": "<a href=\"https://github.com/IISNRL/DCF-PM2.5/blob/master/2024/20240312/20240312-PMS5003-taoyuan.joblib\" target=\"_blank\" title=\"20240312-PMS5003-taoyuan.joblib\">Link to File</a>",
        "Config": "<a href=\"https://github.com/IISNRL/DCF-PM2.5/blob/master/2024/20240312/20240312-PMS5003-taoyuan.json\" target=\"_blank\" title=\"20240312-PMS5003-taoyuan.json\">Link to File</a>"
      },
      "geometry": {
        "type": "Point",
        "coordinates": [
          121.304,
          24.995
        ]
      }
    },
    {
      "type": "Feature",
      "properties": {
        "Feature": "PTR",
        "Method": "GAM",
        "Data_Length": 7,
        "SiteName": "Zhongming",
        "Date": "2024-03-12",
        "Valid_MAE": 2.987,
        "Version": "2024-03-12 00:01:34",
        "Model": "<a href=\"https://github.com/IISNRL/DCF-PM2.5/blob/master/2024/20240312/20240312-PMS5003-zhongming.joblib\" target=\"_blank\" title=\"20240312-PMS5003-zhongming.joblib\">Link to File</a>",
        "Config": "<a href=\"https://github.com/IISNRL/DCF-PM2.5/blob/master/2024/20240312/20240312-PMS5003-zhongming.json\" target=\"_blank\" title=\"20240312-PMS5003-zhongming.json\">Link to File</a>"
      },
      "geometry": {
        "type": "Point",
        "coordinates": [
          120.641,
          24.152
        ]
      }
    },
    {
      "type": "Feature",
      "properties": {
        "Feature": "PTR",
        "Method": "RandomForestRegressor",
        "Data_Length": 14,
        "SiteName": "Wanhua",
        "Date": "2024-03-12",
        "Valid_MAE": 2.929,
        "Version": "2024-03-12 00:01:38",
        "Model": "<a href=\"https://github.com/IISNRL/DCF-PM2.5/blob/master/2024/20240312/20240312-PMS5003-wanhua.joblib\" target=\"_blank\" title=\"20240312-PMS5003-wanhua.joblib\">Link to File</a>",
        "Config": "<a href=\"https://github.com/IISNRL/DCF-PM2.5/blob/master/2024/20240312/20240312-PMS5003-wanhua.json\" target=\"_blank\" title=\"20240312-PMS5003-wanhua.json\">Link to File</a>"
      },
      "geometry": {
        "type": "Point",
        "coordinates": [
          121.508,
          25.047
        ]
      }
    }
  ]
}