{
  "type": "FeatureCollection",
  "features": [
    {
      "type": "Feature",
      "properties": {
        "Feature": "PHR",
        "Method": "SVR",
        "Data_Length": 30,
        "SiteName": "Taoyuan",
        "Date": "2024-05-26",
        "Valid_MAE": 4.144,
        "Version": "2024-05-26 00:01:21",
        "Model": "<a href=\"https://github.com/IISNRL/DCF-PM2.5/blob/master/2024/20240526/20240526-PMS5003-taoyuan.joblib\" target=\"_blank\" title=\"20240526-PMS5003-taoyuan.joblib\">Link to File</a>",
        "Config": "<a href=\"https://github.com/IISNRL/DCF-PM2.5/blob/master/2024/20240526/20240526-PMS5003-taoyuan.json\" target=\"_blank\" title=\"20240526-PMS5003-taoyuan.json\">Link to File</a>"
      },
      "geometry": {
        "type": "Point",
        "coordinates": [
          121.304,
          24.995
        ]
      }
    },
    {
      "type": "Feature",
      "properties": {
        "Feature": "PHTR",
        "Method": "SVR",
        "Data_Length": 21,
        "SiteName": "Zhongming",
        "Date": "2024-05-26",
        "Valid_MAE": 3.097,
        "Version": "2024-05-26 00:01:29",
        "Model": "<a href=\"https://github.com/IISNRL/DCF-PM2.5/blob/master/2024/20240526/20240526-PMS5003-zhongming.joblib\" target=\"_blank\" title=\"20240526-PMS5003-zhongming.joblib\">Link to File</a>",
        "Config": "<a href=\"https://github.com/IISNRL/DCF-PM2.5/blob/master/2024/20240526/20240526-PMS5003-zhongming.json\" target=\"_blank\" title=\"20240526-PMS5003-zhongming.json\">Link to File</a>"
      },
      "geometry": {
        "type": "Point",
        "coordinates": [
          120.641,
          24.152
        ]
      }
    },
    {
      "type": "Feature",
      "properties": {
        "Feature": "PHT",
        "Method": "GAM",
        "Data_Length": 30,
        "SiteName": "Wanhua",
        "Date": "2024-05-26",
        "Valid_MAE": 4.591,
        "Version": "2024-05-26 00:01:30",
        "Model": "<a href=\"https://github.com/IISNRL/DCF-PM2.5/blob/master/2024/20240526/20240526-PMS5003-wanhua.joblib\" target=\"_blank\" title=\"20240526-PMS5003-wanhua.joblib\">Link to File</a>",
        "Config": "<a href=\"https://github.com/IISNRL/DCF-PM2.5/blob/master/2024/20240526/20240526-PMS5003-wanhua.json\" target=\"_blank\" title=\"20240526-PMS5003-wanhua.json\">Link to File</a>"
      },
      "geometry": {
        "type": "Point",
        "coordinates": [
          121.508,
          25.047
        ]
      }
    }
  ]
}