{
  "type": "FeatureCollection",
  "features": [
    {
      "type": "Feature",
      "properties": {
        "Feature": "PHTR",
        "Method": "GAM",
        "Data_Length": 7,
        "SiteName": "Banqiao",
        "Date": "2022-12-31",
        "Valid_MAE": 2.912,
        "Version": "2022-12-31 00:03:20",
        "Model": "<a href=\"https://github.com/IISNRL/DCF-PM2.5/blob/master/2022/20221231/20221231-PMS5003-banqiao.joblib\" target=\"_blank\" title=\"20221231-PMS5003-banqiao.joblib\">Link to File</a>",
        "Config": "<a href=\"https://github.com/IISNRL/DCF-PM2.5/blob/master/2022/20221231/20221231-PMS5003-banqiao.json\" target=\"_blank\" title=\"20221231-PMS5003-banqiao.json\">Link to File</a>"
      },
      "geometry": {
        "type": "Point",
        "coordinates": [
          121.459,
          25.013
        ]
      }
    },
    {
      "type": "Feature",
      "properties": {
        "Feature": "PTR",
        "Method": "GAM",
        "Data_Length": 7,
        "SiteName": "Taoyuan",
        "Date": "2022-12-31",
        "Valid_MAE": 2.286,
        "Version": "2022-12-31 00:03:42",
        "Model": "<a href=\"https://github.com/IISNRL/DCF-PM2.5/blob/master/2022/20221231/20221231-PMS5003-taoyuan.joblib\" target=\"_blank\" title=\"20221231-PMS5003-taoyuan.joblib\">Link to File</a>",
        "Config": "<a href=\"https://github.com/IISNRL/DCF-PM2.5/blob/master/2022/20221231/20221231-PMS5003-taoyuan.json\" target=\"_blank\" title=\"20221231-PMS5003-taoyuan.json\">Link to File</a>"
      },
      "geometry": {
        "type": "Point",
        "coordinates": [
          121.304,
          24.995
        ]
      }
    },
    {
      "type": "Feature",
      "properties": {
        "Feature": "PHR",
        "Method": "SVR",
        "Data_Length": 14,
        "SiteName": "Zhongming",
        "Date": "2022-12-31",
        "Valid_MAE": 2.61,
        "Version": "2022-12-31 00:03:54",
        "Model": "<a href=\"https://github.com/IISNRL/DCF-PM2.5/blob/master/2022/20221231/20221231-PMS5003-zhongming.joblib\" target=\"_blank\" title=\"20221231-PMS5003-zhongming.joblib\">Link to File</a>",
        "Config": "<a href=\"https://github.com/IISNRL/DCF-PM2.5/blob/master/2022/20221231/20221231-PMS5003-zhongming.json\" target=\"_blank\" title=\"20221231-PMS5003-zhongming.json\">Link to File</a>"
      },
      "geometry": {
        "type": "Point",
        "coordinates": [
          120.641,
          24.152
        ]
      }
    },
    {
      "type": "Feature",
      "properties": {
        "Feature": "PHR",
        "Method": "SVR",
        "Data_Length": 30,
        "SiteName": "Wanhua",
        "Date": "2022-12-31",
        "Valid_MAE": 2.198,
        "Version": "2022-12-31 00:04:04",
        "Model": "<a href=\"https://github.com/IISNRL/DCF-PM2.5/blob/master/2022/20221231/20221231-PMS5003-wanhua.joblib\" target=\"_blank\" title=\"20221231-PMS5003-wanhua.joblib\">Link to File</a>",
        "Config": "<a href=\"https://github.com/IISNRL/DCF-PM2.5/blob/master/2022/20221231/20221231-PMS5003-wanhua.json\" target=\"_blank\" title=\"20221231-PMS5003-wanhua.json\">Link to File</a>"
      },
      "geometry": {
        "type": "Point",
        "coordinates": [
          121.508,
          25.047
        ]
      }
    }
  ]
}